MANIFEST.in
README.txt
setup.py
django_reviews.egg-info/PKG-INFO
django_reviews.egg-info/SOURCES.txt
django_reviews.egg-info/dependency_links.txt
django_reviews.egg-info/not-zip-safe
django_reviews.egg-info/requires.txt
django_reviews.egg-info/top_level.txt
reviews/__init__.py
reviews/admin.py
reviews/managers.py
reviews/models.py
reviews/settings.py
reviews/signals.py
reviews/tests.py
reviews/urls.py
reviews/utils.py
reviews/views.py
reviews/example/__init__.py
reviews/migrations/0001_initial.py
reviews/migrations/__init__.py
reviews/templatetags/__init__.py
reviews/templatetags/reviews_tags.py